{
  "availability-zones:account=682033502734:region=eu-west-1": [
    "eu-west-1a",
    "eu-west-1b",
    "eu-west-1c"
  ],
  "availability-zones:account=961341546901:region=eu-west-1": [
    "eu-west-1a",
    "eu-west-1b",
    "eu-west-1c"
  ],
  "availability-zones:account=515966535475:region=eu-west-1": [
    "eu-west-1a",
    "eu-west-1b",
    "eu-west-1c"
  ],
  "hosted-zone:account=682033502734:domainName=kios.untuvaopintopolku.fi:region=eu-west-1": {
    "Id": "/hostedzone/Z10326503D1K4RJPIWZC8",
    "Name": "kios.untuvaopintopolku.fi."
  },
  "hosted-zone:account=515966535475:domainName=kios.opintopolku.fi:region=eu-west-1": {
    "Id": "/hostedzone/Z0178098NKPUAN6HMB78",
    "Name": "kios.opintopolku.fi."
  }
}
